{
    "baselines": [
        {
            "blob": null,
            "detector": "Cup"
        },
        {
            "blob": null,
            "detector": "SEM"
        }
    ],
    "commit": "c2dacc29adeea66f7bb22bca2fa2479daab09c7f",
    "encoding": "base64",
    "format": ">ff",
    "signals": [
        {
            "blob": "QWWpBj/8Pc9BduhJP9EZlUGD9v1AKS4mQYxzvj/7vOJBlPIUP/yTwkGddHJAE5uzQaX0BT/RxXlBrnNtP/wS1Q==",
            "detector": "Cup",
            "isotope": "He4"
        },
        {
            "blob": null,
            "detector": "SEM",
            "isotope": "He3"
        }
    ],
    "sniffs": [
        {
            "blob": "P5FsuD/86bRAD+isP/yTwkBW+Wc//JPCQI9DP0ATWzxAsuHcQCkDLEDWVsJAE1s8QPnHND/8aMhBDsYJP/u84kEgwE0//Om0QTJnUD/8EtU=",
            "detector": "Cup",
            "isotope": "He4"
        },
        {
            "blob": null,
            "detector": "SEM",
            "isotope": "He3"
        }
    ]
}